JesseTradingViewLightReport/__init__.py
JesseTradingViewLightReport/generateReport.py
JesseTradingViewLightReport-1.2.2.dist-info/LICENSE.txt
JesseTradingViewLightReport-1.2.2.dist-info/METADATA
JesseTradingViewLightReport-1.2.2.dist-info/WHEEL
JesseTradingViewLightReport-1.2.2.dist-info/top_level.txt
JesseTradingViewLightReport-1.2.2.dist-info/RECORD
