Metadata-Version: 2.1
Name: JesseTradingViewLightReport
Version: 1.2.2
Summary: Generate an html document containing all of the scripts and data to load tradingview and review the results
Home-page: https://github.com/qwpto/JesseTradingViewLightReport
Author: qwpto
Author-email: 109690977+qwpto@users.noreply.github.com
Project-URL: Bug Reports, https://github.com/qwpto/JesseTradingViewLightReport/issues
Project-URL: Source, https://github.com/qwpto/JesseTradingViewLightReport/
Keywords: jesse,trade,tradingview,report
Classifier: Development Status :: 3 - Alpha
Classifier: Intended Audience :: Developers
Classifier: Topic :: Software Development :: Build Tools
Classifier: License :: OSI Approved :: MIT License
Classifier: Programming Language :: Python :: 3
Classifier: Programming Language :: Python :: 3.7
Classifier: Programming Language :: Python :: 3.8
Classifier: Programming Language :: Python :: 3.9
Classifier: Programming Language :: Python :: 3.10
Classifier: Programming Language :: Python :: 3 :: Only
Requires-Python: >=3.7, <4
License-File: LICENSE.txt
Requires-Dist: jesse
Requires-Dist: pandas
Requires-Dist: bottle
Provides-Extra: dev
Requires-Dist: check-manifest ; extra == 'dev'
Provides-Extra: test
Requires-Dist: coverage ; extra == 'test'
